{
	"backtraceGraph" : 
	{
		"commands" : 
		[
			"install"
		],
		"files" : 
		[
			"plugins/cudart/demo/CMakeLists.txt"
		],
		"nodes" : 
		[
			{
				"file" : 0
			},
			{
				"command" : 0,
				"file" : 0,
				"line" : 4,
				"parent" : 0
			},
			{
				"command" : 0,
				"file" : 0,
				"line" : 8,
				"parent" : 0
			},
			{
				"command" : 0,
				"file" : 0,
				"line" : 12,
				"parent" : 0
			},
			{
				"command" : 0,
				"file" : 0,
				"line" : 16,
				"parent" : 0
			}
		]
	},
	"installers" : 
	[
		{
			"backtrace" : 1,
			"component" : "Unspecified",
			"destination" : "/root/GVirtuS/demo/cudart",
			"paths" : 
			[
				"plugins/cudart/demo/add_grid.e"
			],
			"targetId" : "add_grid.e::@872b28004a884b6c0795",
			"targetIndex" : 0,
			"type" : "target"
		},
		{
			"backtrace" : 2,
			"component" : "Unspecified",
			"destination" : "/root/GVirtuS/demo/cudart",
			"paths" : 
			[
				"plugins/cudart/demo/dummy0.e"
			],
			"targetId" : "dummy0.e::@872b28004a884b6c0795",
			"targetIndex" : 2,
			"type" : "target"
		},
		{
			"backtrace" : 3,
			"component" : "Unspecified",
			"destination" : "/root/GVirtuS/demo/cudart",
			"paths" : 
			[
				"plugins/cudart/demo/launchKernel.e"
			],
			"targetId" : "launchKernel.e::@872b28004a884b6c0795",
			"targetIndex" : 9,
			"type" : "target"
		},
		{
			"backtrace" : 4,
			"component" : "Unspecified",
			"destination" : "/root/GVirtuS/demo/cudart",
			"paths" : 
			[
				"plugins/cudart/demo/matrixMul.e"
			],
			"targetId" : "matrixMul.e::@872b28004a884b6c0795",
			"targetIndex" : 10,
			"type" : "target"
		}
	],
	"paths" : 
	{
		"build" : "plugins/cudart/demo",
		"source" : "plugins/cudart/demo"
	}
}
